torchlie/__init__.py
torchlie/global_params.py
torchlie/lie_tensor.py
torchlie/types.py
torchlie/functional/__init__.py
torchlie/functional/check_contexts.py
torchlie/functional/constants.py
torchlie/functional/lie_group.py
torchlie/functional/se3_impl.py
torchlie/functional/so3_impl.py
torchlie/functional/utils.py
torchlie-0.1.0.dist-info/LICENSE
torchlie-0.1.0.dist-info/METADATA
torchlie-0.1.0.dist-info/WHEEL
torchlie-0.1.0.dist-info/top_level.txt
torchlie-0.1.0.dist-info/RECORD
